{
  "UniqueName": "Angder.Angdermod",
  "Version": "0.10.5",
  "Author": "Angder",
  "Description": "Angder. Adds a violent, aggressive, character to the game.",
  "RequiredApiVersion": "0.6.0",
  "EntryPointAssembly": "Angdermod.dll",
  "Dependencies": [
    {
      "UniqueName": "Shockah.Kokoro",
      "Version": "1.3.1"
    },
    {
        "UniqueName": "TheJazMaster.MoreDifficulties",
        "Version": "1.3.0",
        "IsRequired": false
    }
    ],
    "UpdateChecks": {
        "GitHub": {
            "Repository": "Angderfang/AngderCobolt"
        }
    }

}
